aliyun_logger/__init__.py
aliyun_logger/src/__init__.py
aliyun_logger/src/aliyun_logger.py
aliyun_logger-0.4.dist-info/METADATA
aliyun_logger-0.4.dist-info/WHEEL
aliyun_logger-0.4.dist-info/top_level.txt
aliyun_logger-0.4.dist-info/RECORD
