Metadata-Version: 2.1
Name: aliyun-logger
Version: 0.4
Summary: Python package for 53 Aliyun Logger
Home-page: https://github.com/your_username/aliyun-logger
Author: Yuxiang Zhang
Author-email: zhangyuxiang@53zaixian.com
Classifier: Programming Language :: Python :: 3
Classifier: License :: OSI Approved :: MIT License
Classifier: Operating System :: OS Independent
Requires-Dist: aliyun-log-python-sdk
Requires-Dist: enum34
